{
  "title": "Google Very Angry After Contractor Leaks Over a Thousand Assistant Recordings",
  "description": "Just in case you were holding out any hope that Google didn’t let humans listen to voice recordings from Google Home and Google Assistant, stop doing that. One of the humans that Google hired to review voice recordings recently leaked over a thousand Assistant recordings to a Belgian news organization, which published…",
  "url": "https://gizmodo.com/google-very-angry-after-contractor-leaks-over-a-thousan-1836308139",
  "locale": "en_US",
  "site_name": "Gizmodo",
  "image": {
    "url": "https://i.kinja-img.com/gawker-media/image/upload/c_fill,f_auto,fl_progressive,g_center,h_675,pg_1,q_80,w_1200/dxaa8ce6bcjbvogej85a.jpg"
  },
  "type": "article"
}